Workbook

Sheet raw_fies
A1: TABLE 2.2 Number of Families, Average Annual Income and Expenditure by Region: 2015, 2018, 2021, and 2023
A2: (In thousand PhP; except number of families)
A4: Region | B4: Total Number of Families (in thousands) | C4: Average Income | D4: Average Expenditure | E4: Savings | G4: Total Number of Families (in thousands) | H4: Average Income | J4: Average Expenditure | L4: Savings
A7: 2015 | B7: 22976 | C7: 268 | D7: 216 | E7: 52 | F7: 2021 | G7: 26397 | H7: 307 | J7: 229 | L7: 78
A9: NCR | B9: 3096 | C9: 425 | D9: 349 | E9: 76 | G9: 3512 | H9: 418 | J9: 322
A10: CAR | B10: 396 | C10: 282 | D10: 209 | E10: 73 | G10: 447 | H10: 350 | J10: 243 | L10: 108
A11: I-Ilocos Region | B11: 1152 | C11: 238 | D11: 182 | E11: 56 | G11: 1270 | H11: 305 | J11: 210 | L11: 95
A12: II-Cagayan Valley | B12: 805 | C12: 237 | D12: 162 | E12: 75 | G12: 898 | H12: 290 | J12: 201 | L12: 89
A13: III-Central Luzon | B13: 2567 | C13: 299 | D13: 239 | E13: 60 | G13: 2991 | H13: 329 | J13: 258 | L13: 70
A14: IV-A-CALABARZON | B14: 3395 | C14: 312 | D14: 269 | E14: 43 | G14: 4082 | H14: 361 | J14: 281 | L14: 80
A15: MIMAROPA | B15: 683 | C15: 222 | D15: 161 | E15: 61 | G15: 787 | H15: 255 | J15: 178 | L15: 77
A16: V-Bicol Region | B16: 1216 | C16: 187 | D16: 160 | E16: 27 | G16: 1338 | H16: 252 | J16: 190 | L16: 62
A17: VI-Western Visayas | B17: 1717 | C17: 226 | D17: 176 | E17: 50 | G17: 1945 | H17: 268 | J17: 200 | L17: 68
A18: VII-Central Visayas | B18: 1699 | C18: 239 | D18: 193 | E18: 46 | G18: 1970 | H18: 285 | J18: 194 | L18: 91
A19: VIII-Eastern Visayas | B19: 986 | C19: 197 | D19: 156 | E19: 41 | G19: 1134 | H19: 243 | J19: 189 | L19: 54
A20: IX-Zamboanga Peninsula | B20: 799 | C20: 190 | D20: 144 | E20: 46 | G20: 874 | H20: 239 | J20: 166 | L20: 72
A21: X-Northern Mindanao | B21: 1043 | C21: 221 | D21: 161 | E21: 60 | G21: 1191 | H21: 257 | J21: 176 | L21: 82
... A25: BARMM | B25: 620 | C25: 139 | D25: 111 | E25: 28 | G25: 696 | H25: 185 | J25: 150 | L25: 35
A27: 2018 | B27: 24747 | C27: 313 | D27: 239 | E27: 75 | F27: 2023 | G27: 27480 | H27: 353 | J27: 258 | L27: 95
A29: NCR | B29: 3318 | C29: 460 | D29: 369 | E29: 92 | G29: 3633 | H29: 514 | J29: 385 | L29: 128
A30: CAR | B30: 422 | C30: 354 | D30: 230 | E30: 124 | G30: 464 | H30: 359 | J30: 248 | L30: 111
A31: I-Ilocos Region | B31: 1213 | C31: 287 | D31: 205 | E31: 82 | G31: 1307 | H31: 340 | J31: 232 | L31: 107
A32: II-Cagayan Valley | B32: 853 | C32: 265 | D32: 174 | E32: 91 | G32: 926 | H32: 311 | J32: 214 | L32: 97
A33: III-Central Luzon | B33: 2783 | C33: 334 | D33: 270 | E33: 64 | G33: 3123 | H33: 375 | J33: 299 | L33: 77
A34: IV-A-CALABARZON | B34: 3760 | C34: 384 | D34: 305 | E34: 80 | G34: 4304 | H34: 427 | J34: 310 | L34: 116
A35: MIMAROPA | B35: 737 | C35: 257 | D35: 175 | E35: 83 | G35: 819 | H35: 267 | J35: 190 | L35: 78
A36: V-Bicol Region | B36: 1280 | C36: 235 | D36: 193 | E36: 42 | G36: 1374 | H36: 287 | J36: 203 | L36: 85
A37: VI-Western Visayas | B37: 1832 | C37: 266 | D37: 202 | E37: 63 | G37: 2019 | H37: 298 | J37: 225 | L37: 73
A38: VII-Central Visayas | B38: 1839 | C38: 308 | D38: 204 | E38: 104 | G38: 2053 | H38: 317 | J38: 210 | L38: 107
A39: VIII-Eastern Visayas | B39: 1059 | C39: 227 | D39: 179 | E39: 48 | G39: 1185 | H39: 267 | J39: 200 | L39: 67
A40: IX-Zamboanga Peninsula | B40: 839 | C40: 228 | D40: 162 | E40: 65 | G40: 897 | H40: 257 | J40: 201 | L40: 56
... A45: BARMM | B45: 657 | C45: 161 | D45: 127 | E45: 34 | G45: 837 | H45: 207 | J45: 169 | L45: 38
A48: Note: Details may not add up to totals due to rounding.
A50: Source: Philippine Statistics Authority, 2015, 2018, 2021, and 2023 Family Income and Expenditure Survey

Sheet clean_fies
A1: year | B1: region_raw | C1: region_code | D1: region_name | E1: number_of_families_thousands | F1: avg_annual_income_thousand_php | G1: avg_annual_expenditure_thousand_php | H1: avg_annual_savings_thousand_php | I1: number_of_families | J1: avg_annual_income_php | K1: avg_annual_expenditure_php | L1: avg_annual_savings_php | M1: avg_monthly_income_php | N1: avg_monthly_expenditure_php | O1: avg_monthly_savings_php | P1: savings_rate | Q1: income_to_expenditure_ratio
A2: 2015 | B2: NCR | C2: NCR | D2: National Capital Region | E2: 3096 | F2: 425 | G2: 349 | H2: 76 | I2: 3096000 | J2: 425000 | K2: 349000 | L2: 76000 | M2: 35416.667 | N2: 29083.333 | O2: 6333.3333 | P2: 0.17882353 | Q2: 1.217765
A3: 2015 | B3: CAR | C3: CAR | D3: Cordillera Administrative Region | E3: 396 | F3: 282 | G3: 209 | H3: 73 | I3: 396000 | J3: 282000 | K3: 209000 | L3: 73000 | M3: 23500 | N3: 17416.667 | O3: 6083.3333 | P3: 0.25886525 | Q3: 1.3492823
A4: 2015 | B4: I-Ilocos Region | C4: I | D4: Ilocos Region | E4: 1152 | F4: 238 | G4: 182 | H4: 56 | I4: 1152000 | J4: 238000 | K4: 182000 | L4: 56000 | M4: 19833.333 | N4: 15166.667 | O4: 4666.6667 | P4: 0.23529412 | Q4: 1.3076923
A5: 2015 | B5: II-Cagayan Valley | C5: II | D5: Cagayan Valley | E5: 805 | F5: 237 | G5: 162 | H5: 75 | I5: 805000 | J5: 237000 | K5: 162000 | L5: 75000 | M5: 19750 | N5: 13500 | O5: 6250 | P5: 0.3164557 | Q5: 1.462963
A6: 2015 | B6: III-Central Luzon | C6: III | D6: Central Luzon | E6: 2567 | F6: 299 | G6: 239 | H6: 60 | I6: 2567000 | J6: 299000 | K6: 239000 | L6: 60000 | M6: 24916.667 | N6: 19916.667 | O6: 5000 | P6: 0.2006689 | Q6: 1.251046
A7: 2015 | B7: IV-A-CALABARZON | C7: IV-A | D7: CALABARZON | E7: 3395 | F7: 312 | G7: 269 | H7: 43 | I7: 3395000 | J7: 312000 | K7: 269000 | L7: 43000 | M7: 26000 | N7: 22416.667 | O7: 3583.3333 | P7: 0.13782051 | Q7: 1.1598513
A8: 2015 | B8: MIMAROPA | C8: MIMAROPA | D8: MIMAROPA Region | E8: 683 | F8: 222 | G8: 161 | H8: 61 | I8: 683000 | J8: 222000 | K8: 161000 | L8: 61000 | M8: 18500 | N8: 13416.667 | O8: 5083.3333 | P8: 0.27477477 | Q8: 1.378882
A9: 2015 | B9: V-Bicol Region | C9: V | D9: Bicol Region | E9: 1216 | F9: 187 | G9: 160 | H9: 27 | I9: 1216000 | J9: 187000 | K9: 160000 | L9: 27000 | M9: 15583.333 | N9: 13333.333 | O9: 2250 | P9: 0.14438503 | Q9: 1.16875
A10: 2015 | B10: VI-Western Visayas | C10: VI | D10: Western Visayas | E10: 1717 | F10: 226 | G10: 176 | H10: 50 | I10: 1717000 | J10: 226000 | K10: 176000 | L10: 50000 | M10: 18833.333 | N10: 14666.667 | O10: 4166.6667 | P10: 0.22123894 | Q10: 1.2840909
A11: 2015 | B11: VII-Central Visayas | C11: VII | D11: Central Visayas | E11: 1699 | F11: 239 | G11: 193 | H11: 46 | I11: 1699000 | J11: 239000 | K11: 193000 | L11: 46000 | M11: 19916.667 | N11: 16083.333 | O11: 3833.3333 | P11: 0.19246862 | Q11: 1.238342
A12: 2015 | B12: VIII-Eastern Visayas | C12: VIII | D12: Eastern Visayas | E12: 986 | F12: 197 | G12: 156 | H12: 41 | I12: 986000 | J12: 197000 | K12: 156000 | L12: 41000 | M12: 16416.667 | N12: 13000 | O12: 3416.6667 | P12: 0.20812183 | Q12: 1.2628205
A13: 2015 | B13: IX-Zamboanga Peninsula | C13: IX | D13: Zamboanga Peninsula | E13: 799 | F13: 190 | G13: 144 | H13: 46 | I13: 799000 | J13: 190000 | K13: 144000 | L13: 46000 | M13: 15833.333 | N13: 12000 | O13: 3833.3333 | P13: 0.24210526 | Q13: 1.3194444
... A69: 2023 | B69: BARMM | C69: BARMM | D69: Bangsamoro Autonomous Region in Muslim Mindanao | E69: 837 | F69: 207 | G69: 169 | H69: 38 | I69: 837000 | J69: 207000 | K69: 169000 | L69: 38000 | M69: 17250 | N69: 14083.333 | O69: 3166.6667 | P69: 0.18357488 | Q69: 1.2248521
M70: 0

Sheet raw_ows_table2
A1: Table 2. Average Monthly Basic Pay, Allowance, and Wage Rates of Time-Rated Workers on Full-Time Basis by Region, Philippines: August 2024
A2: (In Philippine Peso and in Establishments Employing 10 and More Workers)
A4: Region | B4: Average Monthly
B5: Basic Pay | C5: Allowance | D5: Wage Rate
A7: PHILIPPINES | B7: 20309.034 | C7: 1234.6142 | D7: 21543.648
A9: National Capital Region | B9: 27318.099 | C9: 1991.6839 | D9: 29309.783
A10: Cordillera Administrative Region | B10: 16548.321 | C10: 884.10789 | D10: 17432.429
A11: Region I - Ilocos Region | B11: 14247.541 | C11: 531.96259 | D11: 14779.503
A12: Region II - Cagayan Valley | B12: 14849.031 | C12: 303.66587 | D12: 15152.697
A13: Region III - Central Luzon | B13: 17372.498 | C13: 901.84947 | D13: 18274.347
A14: Region IV-A - CALABARZON | B14: 18753.729 | C14: 957.73318 | D14: 19711.462
A15: MIMAROPA Region | B15: 13418.198 | C15: 819.85297 | D15: 14238.051
A16: Region V - Bicol Region | B16: 13045.026 | C16: 706.409 | D16: 13751.435
A17: Region VI - Western Visayas | B17: 15326.451 | C17: 777.47092 | D17: 16103.922
A18: Region VII - Central Visayas | B18: 18055.017 | C18: 1028.5164 | D18: 19083.534
A19: Region VIII - Eastern Visayas | B19: 12828.085 | C19: 638.96186 | D19: 13467.046
... A25: Bangsamoro Autonomous Region in Muslim Mindanao | B25: 11168.632 | C25: 326.33003 | D25: 11494.962
A28: Notes: 1. Time-rated workers on full-time basis refers to workers paid on the basis of a time unit of work and who work at jobs with hours of work
A29: equal to or more than those considered as normal or regular to the establishments.
A30: 2. Basic pay refers to pay for normal/regular working time before deductions for employees' social security contributions and withholding
A31: taxes. It excludes overtime, night shift differential and other premium pay; commissions, tips and share of employees in service charge;
A32: and payment in kind.
A33: 3. Allowances refer to regular/guaranteed cash payments. These include living allowance but exclude reimbursements for travel,
A34: entertainment, meals and other expenses, etc. incurred in conducting the business of the employer, cost of uniform/working clothes;
A35: bonuses and gratuities; family allowances.
A36: 4. Wage is the sum of basic pay and regular/guaranteed cash allowances.
A37: 5. Sulu province is still part of BARMM. Provinces under the Negros Island Region are still under Region 6 and Region 8.
A38: Source: Philippine Statistics Authority, 2024 Occupational Wages Survey

Sheet clean_ows_table
A1: year | B1: region_raw | C1: region_code | D1: region_name | E1: avg_monthly_basic_pay_php | F1: avg_monthly_allowance_php | G1: avg_monthly_wage_rate_php | H1: wage_check
A2: 2024 | B2: National Capital Region | C2: NCR | D2: National Capital Region | E2: 27318.1 | F2: 1991.68 | G2: 29309.78 | H2: 0
A3: 2024 | B3: Cordillera Administrative Region | C3: CAR | D3: Cordillera Administrative Region | E3: 16548.32 | F3: 884.11 | G3: 17432.43 | H3: 0
A4: 2024 | B4: Region I - Ilocos Region | C4: I | D4: Ilocos Region | E4: 14247.54 | F4: 531.96 | G4: 14779.5 | H4: 0
A5: 2024 | B5: Region II - Cagayan Valley | C5: II | D5: Cagayan Valley | E5: 14849.03 | F5: 303.67 | G5: 15152.7 | H5: 0
A6: 2024 | B6: Region III - Central Luzon | C6: III | D6: Central Luzon | E6: 17372.5 | F6: 901.85 | G6: 18274.35 | H6: 0
A7: 2024 | B7: Region IV-A - CALABARZON | C7: IV-A | D7: CALABARZON | E7: 18753.73 | F7: 957.73 | G7: 19711.46 | H7: 0
A8: 2024 | B8: MIMAROPA Region | C8: MIMAROPA | D8: MIMAROPA Region | E8: 13418.2 | F8: 819.85 | G8: 14238.05 | H8: 0
A9: 2024 | B9: Region V - Bicol Region | C9: V | D9: Bicol Region | E9: 13045.03 | F9: 706.41 | G9: 13751.43 | H9: 0.01
A10: 2024 | B10: Region VI - Western Visayas | C10: VI | D10: Western Visayas | E10: 15326.45 | F10: 777.47 | G10: 16103.92 | H10: 0
A11: 2024 | B11: Region VII - Central Visayas | C11: VII | D11: Central Visayas | E11: 18055.02 | F11: 1028.52 | G11: 19083.53 | H11: 0.01
A12: 2024 | B12: Region VIII - Eastern Visayas | C12: VIII | D12: Eastern Visayas | E12: 12828.08 | F12: 638.96 | G12: 13467.05 | H12: -0.01
A13: 2024 | B13: Region IX - Zamboanga Peninsula | C13: IX | D13: Zamboanga Peninsula | E13: 11861.93 | F13: 358.42 | G13: 12220.35 | H13: 0
... A18: 2024 | B18: Bangsamoro Autonomous Region in Muslim Mindanao | C18: BARMM | D18: Bangsamoro Autonomous Region in Muslim Mindanao | E18: 11168.63 | F18: 326.33 | G18: 11494.96 | H18: 0

Sheet region_lookup
A1: sort_order | B1: region_code | C1: region_name | D1: fies_region_raw | E1: ows_region_raw | F1: notes
A2: 1 | B2: NCR | C2: National Capital Region | D2: NCR | E2: National Capital Region
A3: 2 | B3: CAR | C3: Cordillera Administrative Region | D3: CAR | E3: Cordillera Administrative Region
A4: 3 | B4: I | C4: Ilocos Region | D4: I-Ilocos Region | E4: Region I - Ilocos Region
A5: 4 | B5: II | C5: Cagayan Valley | D5: II-Cagayan Valley | E5: Region II - Cagayan Valley
A6: 5 | B6: III | C6: Central Luzon | D6: III-Central Luzon | E6: Region III - Central Luzon
A7: 6 | B7: IV-A | C7: CALABARZON | D7: IV-A-CALABARZON | E7: Region IV-A - CALABARZON
A8: 7 | B8: MIMAROPA | C8: MIMAROPA Region | D8: MIMAROPA | E8: MIMAROPA Region
A9: 8 | B9: V | C9: Bicol Region | D9: V-Bicol Region | E9: Region V - Bicol Region
A10: 9 | B10: VI | C10: Western Visayas | D10: VI-Western Visayas | E10: Region VI - Western Visayas
A11: 10 | B11: VII | C11: Central Visayas | D11: VII-Central Visayas | E11: Region VII - Central Visayas
A12: 11 | B12: VIII | C12: Eastern Visayas | D12: VIII-Eastern Visayas | E12: Region VIII - Eastern Visayas
A13: 12 | B13: IX | C13: Zamboanga Peninsula | D13: IX-Zamboanga Peninsula | E13: Region IX - Zamboanga Peninsula
... A18: 17 | B18: BARMM | C18: Bangsamoro Autonomous Region in Muslim Mindanao | D18: BARMM | E18: Bangsamoro Autonomous Region in Muslim Mindanao

Sheet analysis_region_affordability_f
A1: sort_order | B1: region_code | C1: region_name | D1: fies_year | E1: ows_year | F1: number_of_families | G1: avg_monthly_family_income_php | H1: avg_monthly_family_expenditure_php | I1: avg_monthly_family_savings_php | J1: savings_rate | K1: income_to_expenditure_ratio | L1: avg_monthly_basic_pay_php | M1: avg_monthly_allowance_php | N1: avg_monthly_wage_rate_php | O1: wage_to_family_expenditure_ratio_proxy | P1: wage_minus_family_expenditure_proxy_php | Q1: savings_rate_rank | R1: income_expenditure_rank | S1: wage_expenditure_proxy_rank | T1: fies_match_count | U1: ows_match_count | V1: match_status
A2: =region_lookup!A2 -> 1 | B2: =region_lookup!B2 -> NCR | C2: =region_lookup!C2 -> National Capital Region | D2: 2023 | E2: 2024 | F2: =SUMIFS(clean_fies!$I:$I,clean_fies!$A:$A,$D2,clean_fies!$C:$C, $B2) -> 3633000 | G2: =SUMIFS(clean_fies!$M:$M, clean_fies!$A:$A, $D2,clean_fies!$C:$C, $B2) -> 42833.333 | H2: =SUMIFS(clean_fies!$N:$N,clean_fies!$A:$A, $D2, clean_fies!$C:$C, $B2) -> 32083.333 | I2: =SUMIFS(clean_fies!$O:$O, clean_fies!$A:$A, $D2, clean_fies!$C:$C, $B2) -> 10666.667 | J2: =IFERROR(I2/G2, " ") -> 0.24902724 | K2: =IFERROR(G2/H2, " ") -> 1.3350649 | L2: =SUMIFS(clean_ows_table!$E:$E,clean_ows_table!$A:$A, $E2, clean_ows_table!$C:$C, $B2) -> 27318.1 | M2: =SUMIFS(clean_ows_table!$F:$F,clean_ows_table!$A:$A, $E2, clean_ows_table!$C:$C, $B2) -> 1991.68 | N2: =SUMIFS(clean_ows_table!$G:$G,clean_ows_table!$A:$A, $E2, clean_ows_table!$C:$C, $B2) -> 29309.78 | O2: =IFERROR(N2/H2, " ") -> 0.91355158 | P2: =IFERROR(N2-H2, " ") -> -2773.5533 | Q2: =_xlfn.RANK.EQ(J2,$J$2:$J$18,0) -> 12 | R2: =_xlfn.RANK.EQ(K2,$K$2:$K$18, 0) -> 11 | S2: =_xlfn.RANK.EQ(O2,$O$2:$O$18, 0) -> 3 | T2: =COUNTIFS(clean_fies!$A:$A, $D2,clean_fies!$C:$C, $B2) -> 1 | U2: =COUNTIFS(clean_ows_table!$A:$A,$E2,clean_ows_table!$C:$C, $B2) -> 1 | V2: =IF(AND(T2=1,U2=1), "OK", "CHECK") -> OK
A3: =region_lookup!A3 -> 2 | B3: =region_lookup!B3 -> CAR | C3: =region_lookup!C3 -> Cordillera Administrative Region | D3: 2023 | E3: 2024 | F3: =SUMIFS(clean_fies!$I:$I,clean_fies!$A:$A,$D3,clean_fies!$C:$C, $B3) -> 464000 | G3: =SUMIFS(clean_fies!$M:$M, clean_fies!$A:$A, $D3,clean_fies!$C:$C, $B3) -> 29916.667 | H3: =SUMIFS(clean_fies!$N:$N,clean_fies!$A:$A, $D3, clean_fies!$C:$C, $B3) -> 20666.667 | I3: =SUMIFS(clean_fies!$O:$O, clean_fies!$A:$A, $D3, clean_fies!$C:$C, $B3) -> 9250 | J3: =IFERROR(I3/G3, " ") -> 0.3091922 | K3: =IFERROR(G3/H3, " ") -> 1.4475806 | L3: =SUMIFS(clean_ows_table!$E:$E,clean_ows_table!$A:$A, $E3, clean_ows_table!$C:$C, $B3) -> 16548.32 | M3: =SUMIFS(clean_ows_table!$F:$F,clean_ows_table!$A:$A, $E3, clean_ows_table!$C:$C, $B3) -> 884.11 | N3: =SUMIFS(clean_ows_table!$G:$G,clean_ows_table!$A:$A, $E3, clean_ows_table!$C:$C, $B3) -> 17432.43 | O3: =IFERROR(N3/H3, " ") -> 0.84350468 | P3: =IFERROR(N3-H3, " ") -> -3234.2367 | Q3: =_xlfn.RANK.EQ(J3,$J$2:$J$18,0) -> 6 | R3: =_xlfn.RANK.EQ(K3,$K$2:$K$18, 0) -> 6 | S3: =_xlfn.RANK.EQ(O3,$O$2:$O$18, 0) -> 8 | T3: =COUNTIFS(clean_fies!$A:$A, $D3,clean_fies!$C:$C, $B3) -> 1 | U3: =COUNTIFS(clean_ows_table!$A:$A,$E3,clean_ows_table!$C:$C, $B3) -> 1 | V3: =IF(AND(T3=1,U3=1), "OK", "CHECK") -> OK
A4: =region_lookup!A4 -> 3 | B4: =region_lookup!B4 -> I | C4: =region_lookup!C4 -> Ilocos Region | D4: 2023 | E4: 2024 | F4: =SUMIFS(clean_fies!$I:$I,clean_fies!$A:$A,$D4,clean_fies!$C:$C, $B4) -> 1307000 | G4: =SUMIFS(clean_fies!$M:$M, clean_fies!$A:$A, $D4,clean_fies!$C:$C, $B4) -> 28333.333 | H4: =SUMIFS(clean_fies!$N:$N,clean_fies!$A:$A, $D4, clean_fies!$C:$C, $B4) -> 19333.333 | I4: =SUMIFS(clean_fies!$O:$O, clean_fies!$A:$A, $D4, clean_fies!$C:$C, $B4) -> 8916.6667 | J4: =IFERROR(I4/G4, " ") -> 0.31470588 | K4: =IFERROR(G4/H4, " ") -> 1.4655172 | L4: =SUMIFS(clean_ows_table!$E:$E,clean_ows_table!$A:$A, $E4, clean_ows_table!$C:$C, $B4) -> 14247.54 | M4: =SUMIFS(clean_ows_table!$F:$F,clean_ows_table!$A:$A, $E4, clean_ows_table!$C:$C, $B4) -> 531.96 | N4: =SUMIFS(clean_ows_table!$G:$G,clean_ows_table!$A:$A, $E4, clean_ows_table!$C:$C, $B4) -> 14779.5 | O4: =IFERROR(N4/H4, " ") -> 0.7644569 | P4: =IFERROR(N4-H4, " ") -> -4553.8333 | Q4: =_xlfn.RANK.EQ(J4,$J$2:$J$18,0) -> 4 | R4: =_xlfn.RANK.EQ(K4,$K$2:$K$18, 0) -> 3 | S4: =_xlfn.RANK.EQ(O4,$O$2:$O$18, 0) -> 14 | T4: =COUNTIFS(clean_fies!$A:$A, $D4,clean_fies!$C:$C, $B4) -> 1 | U4: =COUNTIFS(clean_ows_table!$A:$A,$E4,clean_ows_table!$C:$C, $B4) -> 1 | V4: =IF(AND(T4=1,U4=1), "OK", "CHECK") -> OK
A5: =region_lookup!A5 -> 4 | B5: =region_lookup!B5 -> II | C5: =region_lookup!C5 -> Cagayan Valley | D5: 2023 | E5: 2024 | F5: =SUMIFS(clean_fies!$I:$I,clean_fies!$A:$A,$D5,clean_fies!$C:$C, $B5) -> 926000 | G5: =SUMIFS(clean_fies!$M:$M, clean_fies!$A:$A, $D5,clean_fies!$C:$C, $B5) -> 25916.667 | H5: =SUMIFS(clean_fies!$N:$N,clean_fies!$A:$A, $D5, clean_fies!$C:$C, $B5) -> 17833.333 | I5: =SUMIFS(clean_fies!$O:$O, clean_fies!$A:$A, $D5, clean_fies!$C:$C, $B5) -> 8083.3333 | J5: =IFERROR(I5/G5, " ") -> 0.31189711 | K5: =IFERROR(G5/H5, " ") -> 1.453271 | L5: =SUMIFS(clean_ows_table!$E:$E,clean_ows_table!$A:$A, $E5, clean_ows_table!$C:$C, $B5) -> 14849.03 | M5: =SUMIFS(clean_ows_table!$F:$F,clean_ows_table!$A:$A, $E5, clean_ows_table!$C:$C, $B5) -> 303.67 | N5: =SUMIFS(clean_ows_table!$G:$G,clean_ows_table!$A:$A, $E5, clean_ows_table!$C:$C, $B5) -> 15152.7 | O5: =IFERROR(N5/H5, " ") -> 0.84968411 | P5: =IFERROR(N5-H5, " ") -> -2680.6333 | Q5: =_xlfn.RANK.EQ(J5,$J$2:$J$18,0) -> 5 | R5: =_xlfn.RANK.EQ(K5,$K$2:$K$18, 0) -> 5 | S5: =_xlfn.RANK.EQ(O5,$O$2:$O$18, 0) -> 7 | T5: =COUNTIFS(clean_fies!$A:$A, $D5,clean_fies!$C:$C, $B5) -> 1 | U5: =COUNTIFS(clean_ows_table!$A:$A,$E5,clean_ows_table!$C:$C, $B5) -> 1 | V5: =IF(AND(T5=1,U5=1), "OK", "CHECK") -> OK
A6: =region_lookup!A6 -> 5 | B6: =region_lookup!B6 -> III | C6: =region_lookup!C6 -> Central Luzon | D6: 2023 | E6: 2024 | F6: =SUMIFS(clean_fies!$I:$I,clean_fies!$A:$A,$D6,clean_fies!$C:$C, $B6) -> 3123000 | G6: =SUMIFS(clean_fies!$M:$M, clean_fies!$A:$A, $D6,clean_fies!$C:$C, $B6) -> 31250 | H6: =SUMIFS(clean_fies!$N:$N,clean_fies!$A:$A, $D6, clean_fies!$C:$C, $B6) -> 24916.667 | I6: =SUMIFS(clean_fies!$O:$O, clean_fies!$A:$A, $D6, clean_fies!$C:$C, $B6) -> 6416.6667 | J6: =IFERROR(I6/G6, " ") -> 0.20533333 | K6: =IFERROR(G6/H6, " ") -> 1.2541806 | L6: =SUMIFS(clean_ows_table!$E:$E,clean_ows_table!$A:$A, $E6, clean_ows_table!$C:$C, $B6) -> 17372.5 | M6: =SUMIFS(clean_ows_table!$F:$F,clean_ows_table!$A:$A, $E6, clean_ows_table!$C:$C, $B6) -> 901.85 | N6: =SUMIFS(clean_ows_table!$G:$G,clean_ows_table!$A:$A, $E6, clean_ows_table!$C:$C, $B6) -> 18274.35 | O6: =IFERROR(N6/H6, " ") -> 0.73341873 | P6: =IFERROR(N6-H6, " ") -> -6642.3167 | Q6: =_xlfn.RANK.EQ(J6,$J$2:$J$18,0) -> 16 | R6: =_xlfn.RANK.EQ(K6,$K$2:$K$18, 0) -> 16 | S6: =_xlfn.RANK.EQ(O6,$O$2:$O$18, 0) -> 16 | T6: =COUNTIFS(clean_fies!$A:$A, $D6,clean_fies!$C:$C, $B6) -> 1 | U6: =COUNTIFS(clean_ows_table!$A:$A,$E6,clean_ows_table!$C:$C, $B6) -> 1 | V6: =IF(AND(T6=1,U6=1), "OK", "CHECK") -> OK
A7: =region_lookup!A7 -> 6 | B7: =region_lookup!B7 -> IV-A | C7: =region_lookup!C7 -> CALABARZON | D7: 2023 | E7: 2024 | F7: =SUMIFS(clean_fies!$I:$I,clean_fies!$A:$A,$D7,clean_fies!$C:$C, $B7) -> 4304000 | G7: =SUMIFS(clean_fies!$M:$M, clean_fies!$A:$A, $D7,clean_fies!$C:$C, $B7) -> 35583.333 | H7: =SUMIFS(clean_fies!$N:$N,clean_fies!$A:$A, $D7, clean_fies!$C:$C, $B7) -> 25833.333 | I7: =SUMIFS(clean_fies!$O:$O, clean_fies!$A:$A, $D7, clean_fies!$C:$C, $B7) -> 9666.6667 | J7: =IFERROR(I7/G7, " ") -> 0.27166276 | K7: =IFERROR(G7/H7, " ") -> 1.3774194 | L7: =SUMIFS(clean_ows_table!$E:$E,clean_ows_table!$A:$A, $E7, clean_ows_table!$C:$C, $B7) -> 18753.73 | M7: =SUMIFS(clean_ows_table!$F:$F,clean_ows_table!$A:$A, $E7, clean_ows_table!$C:$C, $B7) -> 957.73 | N7: =SUMIFS(clean_ows_table!$G:$G,clean_ows_table!$A:$A, $E7, clean_ows_table!$C:$C, $B7) -> 19711.46 | O7: =IFERROR(N7/H7, " ") -> 0.76302426 | P7: =IFERROR(N7-H7, " ") -> -6121.8733 | Q7: =_xlfn.RANK.EQ(J7,$J$2:$J$18,0) -> 10 | R7: =_xlfn.RANK.EQ(K7,$K$2:$K$18, 0) -> 10 | S7: =_xlfn.RANK.EQ(O7,$O$2:$O$18, 0) -> 15 | T7: =COUNTIFS(clean_fies!$A:$A, $D7,clean_fies!$C:$C, $B7) -> 1 | U7: =COUNTIFS(clean_ows_table!$A:$A,$E7,clean_ows_table!$C:$C, $B7) -> 1 | V7: =IF(AND(T7=1,U7=1), "OK", "CHECK") -> OK
A8: =region_lookup!A8 -> 7 | B8: =region_lookup!B8 -> MIMAROPA | C8: =region_lookup!C8 -> MIMAROPA Region | D8: 2023 | E8: 2024 | F8: =SUMIFS(clean_fies!$I:$I,clean_fies!$A:$A,$D8,clean_fies!$C:$C, $B8) -> 819000 | G8: =SUMIFS(clean_fies!$M:$M, clean_fies!$A:$A, $D8,clean_fies!$C:$C, $B8) -> 22250 | H8: =SUMIFS(clean_fies!$N:$N,clean_fies!$A:$A, $D8, clean_fies!$C:$C, $B8) -> 15833.333 | I8: =SUMIFS(clean_fies!$O:$O, clean_fies!$A:$A, $D8, clean_fies!$C:$C, $B8) -> 6500 | J8: =IFERROR(I8/G8, " ") -> 0.29213483 | K8: =IFERROR(G8/H8, " ") -> 1.4052632 | L8: =SUMIFS(clean_ows_table!$E:$E,clean_ows_table!$A:$A, $E8, clean_ows_table!$C:$C, $B8) -> 13418.2 | M8: =SUMIFS(clean_ows_table!$F:$F,clean_ows_table!$A:$A, $E8, clean_ows_table!$C:$C, $B8) -> 819.85 | N8: =SUMIFS(clean_ows_table!$G:$G,clean_ows_table!$A:$A, $E8, clean_ows_table!$C:$C, $B8) -> 14238.05 | O8: =IFERROR(N8/H8, " ") -> 0.89924526 | P8: =IFERROR(N8-H8, " ") -> -1595.2833 | Q8: =_xlfn.RANK.EQ(J8,$J$2:$J$18,0) -> 8 | R8: =_xlfn.RANK.EQ(K8,$K$2:$K$18, 0) -> 8 | S8: =_xlfn.RANK.EQ(O8,$O$2:$O$18, 0) -> 4 | T8: =COUNTIFS(clean_fies!$A:$A, $D8,clean_fies!$C:$C, $B8) -> 1 | U8: =COUNTIFS(clean_ows_table!$A:$A,$E8,clean_ows_table!$C:$C, $B8) -> 1 | V8: =IF(AND(T8=1,U8=1), "OK", "CHECK") -> OK
A9: =region_lookup!A9 -> 8 | B9: =region_lookup!B9 -> V | C9: =region_lookup!C9 -> Bicol Region | D9: 2023 | E9: 2024 | F9: =SUMIFS(clean_fies!$I:$I,clean_fies!$A:$A,$D9,clean_fies!$C:$C, $B9) -> 1374000 | G9: =SUMIFS(clean_fies!$M:$M, clean_fies!$A:$A, $D9,clean_fies!$C:$C, $B9) -> 23916.667 | H9: =SUMIFS(clean_fies!$N:$N,clean_fies!$A:$A, $D9, clean_fies!$C:$C, $B9) -> 16916.667 | I9: =SUMIFS(clean_fies!$O:$O, clean_fies!$A:$A, $D9, clean_fies!$C:$C, $B9) -> 7083.3333 | J9: =IFERROR(I9/G9, " ") -> 0.29616725 | K9: =IFERROR(G9/H9, " ") -> 1.4137931 | L9: =SUMIFS(clean_ows_table!$E:$E,clean_ows_table!$A:$A, $E9, clean_ows_table!$C:$C, $B9) -> 13045.03 | M9: =SUMIFS(clean_ows_table!$F:$F,clean_ows_table!$A:$A, $E9, clean_ows_table!$C:$C, $B9) -> 706.41 | N9: =SUMIFS(clean_ows_table!$G:$G,clean_ows_table!$A:$A, $E9, clean_ows_table!$C:$C, $B9) -> 13751.43 | O9: =IFERROR(N9/H9, " ") -> 0.81289241 | P9: =IFERROR(N9-H9, " ") -> -3165.2367 | Q9: =_xlfn.RANK.EQ(J9,$J$2:$J$18,0) -> 7 | R9: =_xlfn.RANK.EQ(K9,$K$2:$K$18, 0) -> 7 | S9: =_xlfn.RANK.EQ(O9,$O$2:$O$18, 0) -> 10 | T9: =COUNTIFS(clean_fies!$A:$A, $D9,clean_fies!$C:$C, $B9) -> 1 | U9: =COUNTIFS(clean_ows_table!$A:$A,$E9,clean_ows_table!$C:$C, $B9) -> 1 | V9: =IF(AND(T9=1,U9=1), "OK", "CHECK") -> OK
A10: =region_lookup!A10 -> 9 | B10: =region_lookup!B10 -> VI | C10: =region_lookup!C10 -> Western Visayas | D10: 2023 | E10: 2024 | F10: =SUMIFS(clean_fies!$I:$I,clean_fies!$A:$A,$D10,clean_fies!$C:$C, $B10) -> 2019000 | G10: =SUMIFS(clean_fies!$M:$M, clean_fies!$A:$A, $D10,clean_fies!$C:$C, $B10) -> 24833.333 | H10: =SUMIFS(clean_fies!$N:$N,clean_fies!$A:$A, $D10, clean_fies!$C:$C, $B10) -> 18750 | I10: =SUMIFS(clean_fies!$O:$O, clean_fies!$A:$A, $D10, clean_fies!$C:$C, $B10) -> 6083.3333 | J10: =IFERROR(I10/G10, " ") -> 0.24496644 | K10: =IFERROR(G10/H10, " ") -> 1.3244444 | L10: =SUMIFS(clean_ows_table!$E:$E,clean_ows_table!$A:$A, $E10, clean_ows_table!$C:$C, $B10) -> 15326.45 | M10: =SUMIFS(clean_ows_table!$F:$F,clean_ows_table!$A:$A, $E10, clean_ows_table!$C:$C, $B10) -> 777.47 | N10: =SUMIFS(clean_ows_table!$G:$G,clean_ows_table!$A:$A, $E10, clean_ows_table!$C:$C, $B10) -> 16103.92 | O10: =IFERROR(N10/H10, " ") -> 0.85887573 | P10: =IFERROR(N10-H10, " ") -> -2646.08 | Q10: =_xlfn.RANK.EQ(J10,$J$2:$J$18,0) -> 13 | R10: =_xlfn.RANK.EQ(K10,$K$2:$K$18, 0) -> 13 | S10: =_xlfn.RANK.EQ(O10,$O$2:$O$18, 0) -> 5 | T10: =COUNTIFS(clean_fies!$A:$A, $D10,clean_fies!$C:$C, $B10) -> 1 | U10: =COUNTIFS(clean_ows_table!$A:$A,$E10,clean_ows_table!$C:$C, $B10) -> 1 | V10: =IF(AND(T10=1,U10=1), "OK", "CHECK") -> OK
A11: =region_lookup!A11 -> 10 | B11: =region_lookup!B11 -> VII | C11: =region_lookup!C11 -> Central Visayas | D11: 2023 | E11: 2024 | F11: =SUMIFS(clean_fies!$I:$I,clean_fies!$A:$A,$D11,clean_fies!$C:$C, $B11) -> 2053000 | G11: =SUMIFS(clean_fies!$M:$M, clean_fies!$A:$A, $D11,clean_fies!$C:$C, $B11) -> 26416.667 | H11: =SUMIFS(clean_fies!$N:$N,clean_fies!$A:$A, $D11, clean_fies!$C:$C, $B11) -> 17500 | I11: =SUMIFS(clean_fies!$O:$O, clean_fies!$A:$A, $D11, clean_fies!$C:$C, $B11) -> 8916.6667 | J11: =IFERROR(I11/G11, " ") -> 0.33753943 | K11: =IFERROR(G11/H11, " ") -> 1.5095238 | L11: =SUMIFS(clean_ows_table!$E:$E,clean_ows_table!$A:$A, $E11, clean_ows_table!$C:$C, $B11) -> 18055.02 | M11: =SUMIFS(clean_ows_table!$F:$F,clean_ows_table!$A:$A, $E11, clean_ows_table!$C:$C, $B11) -> 1028.52 | N11: =SUMIFS(clean_ows_table!$G:$G,clean_ows_table!$A:$A, $E11, clean_ows_table!$C:$C, $B11) -> 19083.53 | O11: =IFERROR(N11/H11, " ") -> 1.0904874 | P11: =IFERROR(N11-H11, " ") -> 1583.53 | Q11: =_xlfn.RANK.EQ(J11,$J$2:$J$18,0) -> 2 | R11: =_xlfn.RANK.EQ(K11,$K$2:$K$18, 0) -> 2 | S11: =_xlfn.RANK.EQ(O11,$O$2:$O$18, 0) -> 1 | T11: =COUNTIFS(clean_fies!$A:$A, $D11,clean_fies!$C:$C, $B11) -> 1 | U11: =COUNTIFS(clean_ows_table!$A:$A,$E11,clean_ows_table!$C:$C, $B11) -> 1 | V11: =IF(AND(T11=1,U11=1), "OK", "CHECK") -> OK
A12: =region_lookup!A12 -> 11 | B12: =region_lookup!B12 -> VIII | C12: =region_lookup!C12 -> Eastern Visayas | D12: 2023 | E12: 2024 | F12: =SUMIFS(clean_fies!$I:$I,clean_fies!$A:$A,$D12,clean_fies!$C:$C, $B12) -> 1185000 | G12: =SUMIFS(clean_fies!$M:$M, clean_fies!$A:$A, $D12,clean_fies!$C:$C, $B12) -> 22250 | H12: =SUMIFS(clean_fies!$N:$N,clean_fies!$A:$A, $D12, clean_fies!$C:$C, $B12) -> 16666.667 | I12: =SUMIFS(clean_fies!$O:$O, clean_fies!$A:$A, $D12, clean_fies!$C:$C, $B12) -> 5583.3333 | J12: =IFERROR(I12/G12, " ") -> 0.25093633 | K12: =IFERROR(G12/H12, " ") -> 1.335 | L12: =SUMIFS(clean_ows_table!$E:$E,clean_ows_table!$A:$A, $E12, clean_ows_table!$C:$C, $B12) -> 12828.08 | M12: =SUMIFS(clean_ows_table!$F:$F,clean_ows_table!$A:$A, $E12, clean_ows_table!$C:$C, $B12) -> 638.96 | N12: =SUMIFS(clean_ows_table!$G:$G,clean_ows_table!$A:$A, $E12, clean_ows_table!$C:$C, $B12) -> 13467.05 | O12: =IFERROR(N12/H12, " ") -> 0.808023 | P12: =IFERROR(N12-H12, " ") -> -3199.6167 | Q12: =_xlfn.RANK.EQ(J12,$J$2:$J$18,0) -> 11 | R12: =_xlfn.RANK.EQ(K12,$K$2:$K$18, 0) -> 12 | S12: =_xlfn.RANK.EQ(O12,$O$2:$O$18, 0) -> 11 | T12: =COUNTIFS(clean_fies!$A:$A, $D12,clean_fies!$C:$C, $B12) -> 1 | U12: =COUNTIFS(clean_ows_table!$A:$A,$E12,clean_ows_table!$C:$C, $B12) -> 1 | V12: =IF(AND(T12=1,U12=1), "OK", "CHECK") -> OK
A13: =region_lookup!A13 -> 12 | B13: =region_lookup!B13 -> IX | C13: =region_lookup!C13 -> Zamboanga Peninsula | D13: 2023 | E13: 2024 | F13: =SUMIFS(clean_fies!$I:$I,clean_fies!$A:$A,$D13,clean_fies!$C:$C, $B13) -> 897000 | G13: =SUMIFS(clean_fies!$M:$M, clean_fies!$A:$A, $D13,clean_fies!$C:$C, $B13) -> 21416.667 | H13: =SUMIFS(clean_fies!$N:$N,clean_fies!$A:$A, $D13, clean_fies!$C:$C, $B13) -> 16750 | I13: =SUMIFS(clean_fies!$O:$O, clean_fies!$A:$A, $D13, clean_fies!$C:$C, $B13) -> 4666.6667 | J13: =IFERROR(I13/G13, " ") -> 0.21789883 | K13: =IFERROR(G13/H13, " ") -> 1.278607 | L13: =SUMIFS(clean_ows_table!$E:$E,clean_ows_table!$A:$A, $E13, clean_ows_table!$C:$C, $B13) -> 11861.93 | M13: =SUMIFS(clean_ows_table!$F:$F,clean_ows_table!$A:$A, $E13, clean_ows_table!$C:$C, $B13) -> 358.42 | N13: =SUMIFS(clean_ows_table!$G:$G,clean_ows_table!$A:$A, $E13, clean_ows_table!$C:$C, $B13) -> 12220.35 | O13: =IFERROR(N13/H13, " ") -> 0.72957313 | P13: =IFERROR(N13-H13, " ") -> -4529.65 | Q13: =_xlfn.RANK.EQ(J13,$J$2:$J$18,0) -> 15 | R13: =_xlfn.RANK.EQ(K13,$K$2:$K$18, 0) -> 15 | S13: =_xlfn.RANK.EQ(O13,$O$2:$O$18, 0) -> 17 | T13: =COUNTIFS(clean_fies!$A:$A, $D13,clean_fies!$C:$C, $B13) -> 1 | U13: =COUNTIFS(clean_ows_table!$A:$A,$E13,clean_ows_table!$C:$C, $B13) -> 1 | V13: =IF(AND(T13=1,U13=1), "OK", "CHECK") -> OK
... A18: =region_lookup!A18 -> 17 | B18: =region_lookup!B18 -> BARMM | C18: =region_lookup!C18 -> Bangsamoro Autonomous Region in Muslim Mindanao | D18: 2023 | E18: 2024 | F18: =SUMIFS(clean_fies!$I:$I,clean_fies!$A:$A,$D18,clean_fies!$C:$C, $B18) -> 837000 | G18: =SUMIFS(clean_fies!$M:$M, clean_fies!$A:$A, $D18,clean_fies!$C:$C, $B18) -> 17250 | H18: =SUMIFS(clean_fies!$N:$N,clean_fies!$A:$A, $D18, clean_fies!$C:$C, $B18) -> 14083.333 | I18: =SUMIFS(clean_fies!$O:$O, clean_fies!$A:$A, $D18, clean_fies!$C:$C, $B18) -> 3166.6667 | J18: =IFERROR(I18/G18, " ") -> 0.18357488 | K18: =IFERROR(G18/H18, " ") -> 1.2248521 | L18: =SUMIFS(clean_ows_table!$E:$E,clean_ows_table!$A:$A, $E18, clean_ows_table!$C:$C, $B18) -> 11168.63 | M18: =SUMIFS(clean_ows_table!$F:$F,clean_ows_table!$A:$A, $E18, clean_ows_table!$C:$C, $B18) -> 326.33 | N18: =SUMIFS(clean_ows_table!$G:$G,clean_ows_table!$A:$A, $E18, clean_ows_table!$C:$C, $B18) -> 11494.96 | O18: =IFERROR(N18/H18, " ") -> 0.81621018 | P18: =IFERROR(N18-H18, " ") -> -2588.3733 | Q18: =_xlfn.RANK.EQ(J18,$J$2:$J$18,0) -> 17 | R18: =_xlfn.RANK.EQ(K18,$K$2:$K$18, 0) -> 17 | S18: =_xlfn.RANK.EQ(O18,$O$2:$O$18, 0) -> 9 | T18: =COUNTIFS(clean_fies!$A:$A, $D18,clean_fies!$C:$C, $B18) -> 1 | U18: =COUNTIFS(clean_ows_table!$A:$A,$E18,clean_ows_table!$C:$C, $B18) -> 1 | V18: =IF(AND(T18=1,U18=1), "OK", "CHECK") -> OK

Sheet analysis_region_affordability
A1: sort_order | B1: region_code | C1: region_name | D1: fies_year | E1: ows_year | F1: number_of_families | G1: avg_monthly_family_income_php | H1: avg_monthly_family_expenditure_php | I1: avg_monthly_family_savings_php | J1: savings_rate | K1: income_to_expenditure_ratio | L1: avg_monthly_basic_pay_php | M1: avg_monthly_allowance_php | N1: avg_monthly_wage_rate_php | O1: wage_to_family_expenditure_ratio_proxy | P1: wage_minus_family_expenditure_proxy_php | Q1: savings_rate_rank | R1: income_expenditure_rank | S1: wage_expenditure_proxy_rank | T1: fies_match_count | U1: ows_match_count | V1: match_status
A2: 1 | B2: NCR | C2: National Capital Region | D2: 2023 | E2: 2024 | F2: 3633000 | G2: 42833.333 | H2: 32083.333 | I2: 10666.667 | J2: 0.24902724 | K2: 1.3350649 | L2: 27318.1 | M2: 1991.68 | N2: 29309.78 | O2: 0.91355158 | P2: -2773.5533 | Q2: 12 | R2: 11 | S2: 3 | T2: 1 | U2: 1 | V2: OK
A3: 2 | B3: CAR | C3: Cordillera Administrative Region | D3: 2023 | E3: 2024 | F3: 464000 | G3: 29916.667 | H3: 20666.667 | I3: 9250 | J3: 0.3091922 | K3: 1.4475806 | L3: 16548.32 | M3: 884.11 | N3: 17432.43 | O3: 0.84350468 | P3: -3234.2367 | Q3: 6 | R3: 6 | S3: 8 | T3: 1 | U3: 1 | V3: OK
A4: 3 | B4: I | C4: Ilocos Region | D4: 2023 | E4: 2024 | F4: 1307000 | G4: 28333.333 | H4: 19333.333 | I4: 8916.6667 | J4: 0.31470588 | K4: 1.4655172 | L4: 14247.54 | M4: 531.96 | N4: 14779.5 | O4: 0.7644569 | P4: -4553.8333 | Q4: 4 | R4: 3 | S4: 14 | T4: 1 | U4: 1 | V4: OK
A5: 4 | B5: II | C5: Cagayan Valley | D5: 2023 | E5: 2024 | F5: 926000 | G5: 25916.667 | H5: 17833.333 | I5: 8083.3333 | J5: 0.31189711 | K5: 1.453271 | L5: 14849.03 | M5: 303.67 | N5: 15152.7 | O5: 0.84968411 | P5: -2680.6333 | Q5: 5 | R5: 5 | S5: 7 | T5: 1 | U5: 1 | V5: OK
A6: 5 | B6: III | C6: Central Luzon | D6: 2023 | E6: 2024 | F6: 3123000 | G6: 31250 | H6: 24916.667 | I6: 6416.6667 | J6: 0.20533333 | K6: 1.2541806 | L6: 17372.5 | M6: 901.85 | N6: 18274.35 | O6: 0.73341873 | P6: -6642.3167 | Q6: 16 | R6: 16 | S6: 16 | T6: 1 | U6: 1 | V6: OK
A7: 6 | B7: IV-A | C7: CALABARZON | D7: 2023 | E7: 2024 | F7: 4304000 | G7: 35583.333 | H7: 25833.333 | I7: 9666.6667 | J7: 0.27166276 | K7: 1.3774194 | L7: 18753.73 | M7: 957.73 | N7: 19711.46 | O7: 0.76302426 | P7: -6121.8733 | Q7: 10 | R7: 10 | S7: 15 | T7: 1 | U7: 1 | V7: OK
A8: 7 | B8: MIMAROPA | C8: MIMAROPA Region | D8: 2023 | E8: 2024 | F8: 819000 | G8: 22250 | H8: 15833.333 | I8: 6500 | J8: 0.29213483 | K8: 1.4052632 | L8: 13418.2 | M8: 819.85 | N8: 14238.05 | O8: 0.89924526 | P8: -1595.2833 | Q8: 8 | R8: 8 | S8: 4 | T8: 1 | U8: 1 | V8: OK
A9: 8 | B9: V | C9: Bicol Region | D9: 2023 | E9: 2024 | F9: 1374000 | G9: 23916.667 | H9: 16916.667 | I9: 7083.3333 | J9: 0.29616725 | K9: 1.4137931 | L9: 13045.03 | M9: 706.41 | N9: 13751.43 | O9: 0.81289241 | P9: -3165.2367 | Q9: 7 | R9: 7 | S9: 10 | T9: 1 | U9: 1 | V9: OK
A10: 9 | B10: VI | C10: Western Visayas | D10: 2023 | E10: 2024 | F10: 2019000 | G10: 24833.333 | H10: 18750 | I10: 6083.3333 | J10: 0.24496644 | K10: 1.3244444 | L10: 15326.45 | M10: 777.47 | N10: 16103.92 | O10: 0.85887573 | P10: -2646.08 | Q10: 13 | R10: 13 | S10: 5 | T10: 1 | U10: 1 | V10: OK
A11: 10 | B11: VII | C11: Central Visayas | D11: 2023 | E11: 2024 | F11: 2053000 | G11: 26416.667 | H11: 17500 | I11: 8916.6667 | J11: 0.33753943 | K11: 1.5095238 | L11: 18055.02 | M11: 1028.52 | N11: 19083.53 | O11: 1.0904874 | P11: 1583.53 | Q11: 2 | R11: 2 | S11: 1 | T11: 1 | U11: 1 | V11: OK
A12: 11 | B12: VIII | C12: Eastern Visayas | D12: 2023 | E12: 2024 | F12: 1185000 | G12: 22250 | H12: 16666.667 | I12: 5583.3333 | J12: 0.25093633 | K12: 1.335 | L12: 12828.08 | M12: 638.96 | N12: 13467.05 | O12: 0.808023 | P12: -3199.6167 | Q12: 11 | R12: 12 | S12: 11 | T12: 1 | U12: 1 | V12: OK
A13: 12 | B13: IX | C13: Zamboanga Peninsula | D13: 2023 | E13: 2024 | F13: 897000 | G13: 21416.667 | H13: 16750 | I13: 4666.6667 | J13: 0.21789883 | K13: 1.278607 | L13: 11861.93 | M13: 358.42 | N13: 12220.35 | O13: 0.72957313 | P13: -4529.65 | Q13: 15 | R13: 15 | S13: 17 | T13: 1 | U13: 1 | V13: OK
... A18: 17 | B18: BARMM | C18: Bangsamoro Autonomous Region in Muslim Mindanao | D18: 2023 | E18: 2024 | F18: 837000 | G18: 17250 | H18: 14083.333 | I18: 3166.6667 | J18: 0.18357488 | K18: 1.2248521 | L18: 11168.63 | M18: 326.33 | N18: 11494.96 | O18: 0.81621018 | P18: -2588.3733 | Q18: 17 | R18: 17 | S18: 9 | T18: 1 | U18: 1 | V18: OK

Sheet dashboard_data
A1: Region | B1: Savings Rate | D1: Region | E1: Monthly Income | F1: Monthly Expenditure | H1: Region | I1: Wage-to-Expenditure Proxy | K1: Region Group | L1: Monthly Income | M1: Monthly Expenditure | N1: Monthly Savings
A2: Davao Region | B2: 0.36050157 | D2: National Capital Region | E2: 42833.333 | F2: 32083.333 | H2: Central Visayas | I2: 1.0904874 | K2: NCR | L2: 42833.33 | M2: 32083.33 | N2: 10666.67
A3: Central Visayas | B3: 0.33753943 | D3: CALABARZON | E3: 35583.333 | F3: 25833.333 | H3: Davao Region | I3: 1.0560476 | K3: Other Regions | L3: 25447.92 | M3: 18348.96 | N3: 7104.17
A4: Northern Mindanao | B4: 0.31756757 | D4: Central Luzon | E4: 31250 | F4: 24916.667 | H4: National Capital Region | I4: 0.91355158
A5: Ilocos Region | B5: 0.31470588 | D5: Cordillera Administrative Region | E5: 29916.667 | F5: 20666.667 | H5: MIMAROPA Region | I5: 0.89924526
A6: Cagayan Valley | B6: 0.31189711 | D6: Ilocos Region | E6: 28333.333 | F6: 19333.333 | H6: Western Visayas | I6: 0.85887573
A7: Cordillera Administrative Region | B7: 0.3091922 | D7: Davao Region | E7: 26583.333 | F7: 17000 | H7: Northern Mindanao | I7: 0.85826305
A8: Bicol Region | B8: 0.29616725 | D8: Central Visayas | E8: 26416.667 | F8: 17500 | H8: Cagayan Valley | I8: 0.84968411
A9: MIMAROPA Region | B9: 0.29213483 | D9: Cagayan Valley | E9: 25916.667 | F9: 17833.333 | H9: Cordillera Administrative Region | I9: 0.84350468
A10: SOCCSKSARGEN | B10: 0.28368794 | D10: Western Visayas | E10: 24833.333 | F10: 18750 | H10: Bangsamoro Autonomous Region in Muslim Mindanao | I10: 0.81621018
A11: CALABARZON | B11: 0.27166276 | D11: Northern Mindanao | E11: 24666.667 | F11: 16916.667 | H11: Bicol Region | I11: 0.81289241
A12: Eastern Visayas | B12: 0.25093633 | D12: Bicol Region | E12: 23916.667 | F12: 16916.667 | H12: Eastern Visayas | I12: 0.808023
A13: National Capital Region | B13: 0.24902724 | D13: SOCCSKSARGEN | E13: 23500 | F13: 16833.333 | H13: Caraga | I13: 0.80108563
A14: Western Visayas | B14: 0.24496644 | D14: Caraga | E14: 23083.333 | F14: 17750 | H14: SOCCSKSARGEN | I14: 0.78047644
A15: Caraga | B15: 0.22743682 | D15: MIMAROPA Region | E15: 22250 | F15: 15833.333 | H15: Ilocos Region | I15: 0.7644569
... A18: Bangsamoro Autonomous Region in Muslim Mindanao | B18: 0.18357488 | D18: Bangsamoro Autonomous Region in Muslim Mindanao | E18: 17250 | F18: 14083.333 | H18: Zamboanga Peninsula | I18: 0.72957313

Sheet dashboard
A1: Where Can Filipinos Get the Most Financial Breathing Room? Regional Income, Expenditure, Savings, and Wage Analysis
A3: Highest Income: National Capital Region ₱ 42, 833.33 | D3: Highest Savings Rate: Davao Region 36.1 % | G3: Best Wage Proxy: Central Visayas 1.09 | J3: NCR Saving Rate: 24.9 %
A39: Note: This is a proxy because wage refers to an individual worker, while expenditure refers to average family expenditure
A41: Key Findings / Notes
A42: 1. NCR had the highest monthly family income, but also the highest monthly family expenditure.
A43: 2. Davao Region had the highest savings rate at 36.1%, suggesting stronger financial breathing room.
A44: 3. Other regions had a higher average savings rate than NCR, despite NCR having much higher income and wage levels.
